ccautils/__init__.py
ccautils/errors.py
ccautils/fileutils.py
ccautils/utils.py
ccautils-0.4.2.dist-info/LICENSE
ccautils-0.4.2.dist-info/WHEEL
ccautils-0.4.2.dist-info/METADATA
ccautils-0.4.2.dist-info/RECORD
