Metadata-Version: 2.1
Name: ccautils
Version: 0.4.2
Summary: A set of useful utilities for python programs
Home-page: https://github.com/ccdale/ccautils
License: GPL-3.0-or-later
Author: ccdale
Author-email: chris.charles.allison+ccautils@gmail.com
Requires-Python: >=3.6,<4.0
Classifier: License :: OSI Approved :: GNU General Public License v3 or later (GPLv3+)
Classifier: Programming Language :: Python :: 3
Classifier: Programming Language :: Python :: 3.6
Classifier: Programming Language :: Python :: 3.7
Classifier: Programming Language :: Python :: 3.8
Requires-Dist: python-dateutil (>=2.8.1,<3.0.0)
Requires-Dist: toml (>=0.10.0,<0.11.0)
Project-URL: Repository, https://github.com/ccdale/ccautils
